membertools/__init__.py
membertools/admin.py
membertools/app_settings.py
membertools/apps.py
membertools/auth_hooks.py
membertools/checks.py
membertools/forms.py
membertools/helpers.py
membertools/managers.py
membertools/models.py
membertools/providers.py
membertools/signals.py
membertools/swagger.json
membertools/tasks.py
membertools/urls_admin.py
membertools/urls_app.py
membertools/views.py
membertools/management/commands/__init__.py
membertools/management/commands/membertools_create_members.py
membertools/management/commands/membertools_import_hrappsnext.py
membertools/management/commands/membertools_setup_perms.py
membertools/migrations/0001_initial.py
membertools/migrations/0002_titlefilter.py
membertools/migrations/0003_implement_titlefilter_add_title_requirement_flag.py
membertools/migrations/0004_alter_charactercorphistory_options.py
membertools/migrations/__init__.py
membertools/static/membertools/css/membertools-base.css
membertools/static/membertools/js/membertools-admin.js
membertools/templates/membertools/app_archive.html
membertools/templates/membertools/app_create.html
membertools/templates/membertools/app_view.html
membertools/templates/membertools/base.html
membertools/templates/membertools/dashboard.html
membertools/templates/membertools/partials/app_status_banner.html
membertools/templates/membertools/partials/app_status_label.html
membertools/templates/membertools/partials/appdetails_app.html
membertools/templates/membertools/partials/applist_app.html
membertools/templates/membertools/partials/checks_app.html
membertools/templates/membertools/partials/corp_history_list.html
membertools/templates/membertools/partials/menu_app.html
membertools/templates/membertools_admin/app_archive.html
membertools/templates/membertools_admin/app_queue.html
membertools/templates/membertools_admin/app_view.html
membertools/templates/membertools_admin/base.html
membertools/templates/membertools_admin/char_detail_index.html
aa_membertools-0.2.1.dist-info/LICENSE
aa_membertools-0.2.1.dist-info/METADATA
aa_membertools-0.2.1.dist-info/WHEEL
aa_membertools-0.2.1.dist-info/top_level.txt
aa_membertools-0.2.1.dist-info/RECORD
