Metadata-Version: 2.1
Name: aa_membertools
Version: 0.2.1
Summary: EVE University Member Tools Plugin for Alliance Auth
Home-page: https://github.com/EVE-University/aa-membertools
Author: Marn Vermuldir
Author-email: marn@minin.io
Maintainer: Marn Vermuldir
Maintainer-email: marn@minin.io
License: GPL-2.0
Project-URL: Issue / Bug Reports, https://github.com/EVE-University/aa-membertools/issues
Project-URL: Changelog, https://github.com/EVE-University/aa-membertools/blob/master/CHANGELOG.md
Keywords: allianceauth,membertools
Classifier: Environment :: Web Environment
Classifier: Framework :: Django
Classifier: Framework :: Django :: 4.0
Classifier: Intended Audience :: Developers
Classifier: License :: OSI Approved :: GNU General Public License v2 (GPLv2)
Classifier: Operating System :: OS Independent
Classifier: Programming Language :: Python
Classifier: Programming Language :: Python :: 3
Classifier: Programming Language :: Python :: 3.8
Classifier: Programming Language :: Python :: 3.9
Classifier: Programming Language :: Python :: 3.10
Classifier: Topic :: Internet :: WWW/HTTP
Classifier: Topic :: Internet :: WWW/HTTP :: Dynamic Content
Requires-Python: ~=3.8
License-File: LICENSE
Requires-Dist: aa-memberaudit>=3.5.0
Requires-Dist: allianceauth>=4.0.0
Requires-Dist: allianceauth-app-utils>=1.8.2
Requires-Dist: celery-once>=2.0.1
Requires-Dist: django-eveuniverse>=0.8.1
Requires-Dist: humanize
Requires-Dist: python-dateutil
Requires-Dist: requests
